FIFO/result/design.sv
module FIFO(input clk, rst, wr, rd, 
            input [7:0] din,output reg [7:0] dout,
            output  empty, full);
  
  reg [3:0] wptr = 0,rptr = 0;
  reg [4:0] cnt = 0;
  reg [7:0] mem [15:0];
  
  always@(posedge clk)
    begin
      if(rst== 1'b1)
         begin
           wptr <= 0;
           rptr <= 0;
           cnt  <= 0;
         end
      else if(wr && !full)
          begin
            mem[wptr] <= din;
            wptr      <= wptr + 1;
            cnt       <= cnt + 1;
            end
      else if (rd && !empty)
         begin
          dout <= mem[rptr];
          rptr <= rptr + 1;
          cnt  <= cnt  - 1;
          end
        end 
 
  
  
  
  assign empty = (cnt == 0)    ? 1'b1 : 1'b0;
  assign full  = (cnt == 16)   ? 1'b1 : 1'b0;
  
endmodule

FIFO/result/testbench.sv
module tb;
	logic clk, rst, wr, rd;
	logic [7:0] din;
	logic [7:0] dout;
	logic empty, full;
	
	FIFO DUT(clk,rst,wr,rd,din,dout,empty,full);
	
	//Clock 
	always #5 clk = ~clk;
	
	//FIFO Reset condition
	initial begin
		clk =0;
		rst = 1;
		wr=0;
		rd=0;
		repeat (5) @(posedge clk);
		rst = 0;
		write();
		read();
	end
	
	// write task
	task write();
		for (int i=0; i<20; i++)begin
			rst = 0;
			wr = 1;
			rd = 0;
			din = $urandom;
			@(posedge clk);
			$display("wr: %0d, addr : %0d, din : %0d full:%0d", wr, i, din, full);
			wr=0;
			@(posedge clk);
		end
	endtask
	
	// Read task
	
	task read();
		for (int i=0; i<20; i++)begin
			rst = 0;
			wr = 0;
			rd = 1;
			@(posedge clk);
			rd=0;
			@(posedge clk);
          			$display("rd: %0d, addr : %0d, dout : %0d empty : %0d", rd, i, dout,empty);
          
		end
	endtask
	
	
	covergroup cvr_fifo @(posedge clk);
		option.per_instance = 1;
		
		coverpoint rst{
			bins rst_low ={0};
			bins rst_hgih = {1};
		}
		
		coverpoint wr{
			bins wr_low ={0};
			bins wr_hgih = {1};
		}
		
		coverpoint rd{
			bins rd_low ={0};
			bins rd_hgih = {1};
		}
		
		coverpoint empty{
			bins empty_low ={0};
			bins empty_hgih = {1};
		}
		
		coverpoint full{
			bins full_low ={0};
			bins full_hgih = {1};
		}
		
		coverpoint din{
			bins din_lower = {[0:84]};
			bins din_medium = {[85:169]};
			bins din_higher = {[170:255]};
		}
		
		coverpoint dout{
			bins dout_lower = {[0:84]};
			bins dout_medium = {[85:169]};
			bins dout_higher = {[170:255]};
		}
		
		//cross coverage b/w rst and wr
		cross_rst_wr: cross rst,wr{
			ignore_bins others_rst = binsof (rst) intersect {1};
			ignore_bins others_wr = binsof (wr) intersect {0};
		}
		
		cross_rst_rd: cross rst,rd{
			ignore_bins others_rst = binsof (rst) intersect {1};
			ignore_bins others_rd = binsof (rd) intersect {0};
		}
		
		cross_wr_din: cross rst,wr,din{
			ignore_bins others_rst = binsof (rst) intersect {1};
			ignore_bins others_wr = binsof (wr) intersect {0};
		}
		
		cross_rd_dout: cross rst,rd,dout{
			ignore_bins others_rst = binsof (rst) intersect {1};
			ignore_bins others_rd = binsof (rd) intersect {0};
		}
		
		cross_wr_full: cross rst,wr,full{
			ignore_bins others_rst = binsof (rst) intersect {1};
			ignore_bins others_wr = binsof (wr) intersect {0};
			ignore_bins others_full = binsof (full) intersect {0};
		}
		
	    cross_rd_empty: cross rst,rd,empty{
			ignore_bins others_rst = binsof (rst) intersect {1};
			ignore_bins others_rd = binsof (rd) intersect {0};
			ignore_bins others_empty = binsof (empty) intersect {0};
		}
		
	endgroup
	
	cvr_fifo c1;
	
	initial begin
		c1 = new();
		$dumpfile("dump.vcd");
		$dumpvars;
		repeat (1200) @(posedge clk);
		$finish();
	end
	
endmodule

FIFO/result/dump.vcd
$date
Tue Dec 26 23:12:05 2023
$end
$version
Riviera-PRO Version 2022.04.117.8517
$end
$timescale
1 ns
$end

$scope module tb $end
$var reg 1 ! clk $end
$var reg 1 " rst $end
$var reg 1 # wr $end
$var reg 1 $ rd $end
$var reg 8 % din [7:0] $end
$var reg 8 & dout [7:0] $end
$var reg 1 ' empty $end
$var reg 1 ( full $end

$scope module DUT $end
$var wire 1 ) clk $end
$var wire 1 * rst $end
$var wire 1 + wr $end
$var wire 1 , rd $end
$var wire 8 - din [7:0] $end
$var wire 1 . empty $end
$var wire 1 / full $end
$var reg 8 0 dout [7:0] $end
$var reg 4 1 wptr [3:0] $end
$var reg 4 2 rptr [3:0] $end
$var reg 5 3 cnt [4:0] $end
$upscope $end


$scope task write $end
$upscope $end


$scope task read $end
$upscope $end

$upscope $end

$enddefinitions $end
$dumpvars
0!
1"
0#
0$
bx %
bx &
1'
0(
0)
1*
0+
0,
bx -
1.
0/
bx 0
b0 1
b0 2
b0 3
$end
#5
1!
1)
#10
0!
0)
#15
1!
1)
#20
0!
0)
#25
1!
1)
#30
0!
0)
#35
1!
1)
#40
0!
0)
#45
1!
1)
0"
1#
b10110011 %
b10110011 -
1+
0*
#50
0!
0)
#55
1!
1)
0#
0+
b1 1
b1 3
0.
0'
#60
0!
0)
#65
1!
1)
1#
b11111 %
b11111 -
1+
#70
0!
0)
#75
1!
1)
0#
0+
b10 1
b10 3
#80
0!
0)
#85
1!
1)
1#
b11000000 %
b11000000 -
1+
#90
0!
0)
#95
1!
1)
0#
0+
b11 1
b11 3
#100
0!
0)
#105
1!
1)
1#
b111010 %
b111010 -
1+
#110
0!
0)
#115
1!
1)
0#
0+
b100 1
b100 3
#120
0!
0)
#125
1!
1)
1#
b11110000 %
b11110000 -
1+
#130
0!
0)
#135
1!
1)
0#
0+
b101 1
b101 3
#140
0!
0)
#145
1!
1)
1#
b1000101 %
b1000101 -
1+
#150
0!
0)
#155
1!
1)
0#
0+
b110 1
b110 3
#160
0!
0)
#165
1!
1)
1#
b1111110 %
b1111110 -
1+
#170
0!
0)
#175
1!
1)
0#
0+
b111 1
b111 3
#180
0!
0)
#185
1!
1)
1#
b1101100 %
b1101100 -
1+
#190
0!
0)
#195
1!
1)
0#
0+
b1000 1
b1000 3
#200
0!
0)
#205
1!
1)
1#
b111101 %
b111101 -
1+
#210
0!
0)
#215
1!
1)
0#
0+
b1001 1
b1001 3
#220
0!
0)
#225
1!
1)
1#
b11110110 %
b11110110 -
1+
#230
0!
0)
#235
1!
1)
0#
0+
b1010 1
b1010 3
#240
0!
0)
#245
1!
1)
1#
b1100 %
b1100 -
1+
#250
0!
0)
#255
1!
1)
0#
0+
b1011 1
b1011 3
#260
0!
0)
#265
1!
1)
1#
b11100001 %
b11100001 -
1+
#270
0!
0)
#275
1!
1)
0#
0+
b1100 1
b1100 3
#280
0!
0)
#285
1!
1)
1#
b11111 %
b11111 -
1+
#290
0!
0)
#295
1!
1)
0#
0+
b1101 1
b1101 3
#300
0!
0)
#305
1!
1)
1#
b110100 %
b110100 -
1+
#310
0!
0)
#315
1!
1)
0#
0+
b1110 1
b1110 3
#320
0!
0)
#325
1!
1)
1#
b10101010 %
b10101010 -
1+
#330
0!
0)
#335
1!
1)
0#
0+
b1111 1
b1111 3
#340
0!
0)
#345
1!
1)
1#
b11100100 %
b11100100 -
1+
#350
0!
0)
#355
1!
1)
0#
0+
b0 1
b10000 3
1/
1(
#360
0!
0)
#365
1!
1)
1#
b10101001 %
b10101001 -
1+
#370
0!
0)
#375
1!
1)
0#
0+
#380
0!
0)
#385
1!
1)
1#
b10000000 %
b10000000 -
1+
#390
0!
0)
#395
1!
1)
0#
0+
#400
0!
0)
#405
1!
1)
1#
b11011011 %
b11011011 -
1+
#410
0!
0)
#415
1!
1)
0#
0+
#420
0!
0)
#425
1!
1)
1#
b100 %
b100 -
1+
#430
0!
0)
#435
1!
1)
0#
0+
#440
0!
0)
#445
1!
1)
1$
1,
#450
0!
0)
#455
1!
1)
0$
0,
b10110011 0
b1 2
b1111 3
b10110011 &
0/
0(
#460
0!
0)
#465
1!
1)
1$
1,
#470
0!
0)
#475
1!
1)
0$
0,
b11111 0
b10 2
b1110 3
b11111 &
#480
0!
0)
#485
1!
1)
1$
1,
#490
0!
0)
#495
1!
1)
0$
0,
b11000000 0
b11 2
b1101 3
b11000000 &
#500
0!
0)
#505
1!
1)
1$
1,
#510
0!
0)
#515
1!
1)
0$
0,
b111010 0
b100 2
b1100 3
b111010 &
#520
0!
0)
#525
1!
1)
1$
1,
#530
0!
0)
#535
1!
1)
0$
0,
b11110000 0
b101 2
b1011 3
b11110000 &
#540
0!
0)
#545
1!
1)
1$
1,
#550
0!
0)
#555
1!
1)
0$
0,
b1000101 0
b110 2
b1010 3
b1000101 &
#560
0!
0)
#565
1!
1)
1$
1,
#570
0!
0)
#575
1!
1)
0$
0,
b1111110 0
b111 2
b1001 3
b1111110 &
#580
0!
0)
#585
1!
1)
1$
1,
#590
0!
0)
#595
1!
1)
0$
0,
b1101100 0
b1000 2
b1000 3
b1101100 &
#600
0!
0)
#605
1!
1)
1$
1,
#610
0!
0)
#615
1!
1)
0$
0,
b111101 0
b1001 2
b111 3
b111101 &
#620
0!
0)
#625
1!
1)
1$
1,
#630
0!
0)
#635
1!
1)
0$
0,
b11110110 0
b1010 2
b110 3
b11110110 &
#640
0!
0)
#645
1!
1)
1$
1,
#650
0!
0)
#655
1!
1)
0$
0,
b1100 0
b1011 2
b101 3
b1100 &
#660
0!
0)
#665
1!
1)
1$
1,
#670
0!
0)
#675
1!
1)
0$
0,
b11100001 0
b1100 2
b100 3
b11100001 &
#680
0!
0)
#685
1!
1)
1$
1,
#690
0!
0)
#695
1!
1)
0$
0,
b11111 0
b1101 2
b11 3
b11111 &
#700
0!
0)
#705
1!
1)
1$
1,
#710
0!
0)
#715
1!
1)
0$
0,
b110100 0
b1110 2
b10 3
b110100 &
#720
0!
0)
#725
1!
1)
1$
1,
#730
0!
0)
#735
1!
1)
0$
0,
b10101010 0
b1111 2
b1 3
b10101010 &
#740
0!
0)
#745
1!
1)
1$
1,
#750
0!
0)
#755
1!
1)
0$
0,
b11100100 0
b0 2
b0 3
b11100100 &
1.
1'
#760
0!
0)
#765
1!
1)
1$
1,
#770
0!
0)
#775
1!
1)
0$
0,
#780
0!
0)
#785
1!
1)
1$
1,
#790
0!
0)
#795
1!
1)
0$
0,
#800
0!
0)
#805
1!
1)
1$
1,
#810
0!
0)
#815
1!
1)
0$
0,
#820
0!
0)
#825
1!
1)
1$
1,
#830
0!
0)
#835
1!
1)
0$
0,
