DAC_SPI/DAC_SPI.sv
module dac(
	input clk,
	input [11:0] din,
	input start,
	output reg mosi, cs
);
  
	typedef enum {idle = 0, init = 1, send = 3, data_gen = 2, cont= 4} state_type;
	state_type state;
 
	reg [31:0] setup = 32'h08000001;
	reg [31:0] dac_data = 32'h00000000;
	integer count = 0;
 
	always@(posedge clk)begin
		case(state)
  
			idle: 
				begin
					cs <= 1'b1;
					mosi <= 1'b0;
 
					if(start)
						state <= init;
					else
						state <= idle;
				end
 
			init:
				begin
					if(count < 32) begin
						count <= count + 1;
						mosi <= setup[31 - count]; //sending unique code to DAC
						cs <= 1'b0; 
						state <= init;
					end
					else begin
						cs <= 1'b1;
						count <= 0;
						state <= data_gen;
					end
 
				end
 
			data_gen: begin
						dac_data <= {12'h030,din,8'h00};
						state <= send;
					end
 
			send: begin
					if(count < 32) begin
						count <= count + 1;
						mosi <= dac_data[31 - count];
						cs <= 1'b0;
						state <= send;
					end
					else begin
						cs <= 1'b1;
						count <= 0;
						state <= cont;
					end
				end
 
			cont: begin
					if(start)
						state <= data_gen;
					else
						state <= idle;
				end
 
		endcase
	end
endmodule

DAC_SPI/tb.sv
module tb;
	logic clk=0;
	logic [11:0] din;
	logic start;
	logic mosi, cs;
	
	dac dut (clk,din,start,mosi,cs);
	
	always #5 clk = ~clk;
	
	initial begin
		start =0;
		#20;
		start=1;
		#2000;
        start=0;
        #20;
		end


	initial begin
      for(int i = 0; i< 200; i++) begin
			@(posedge clk);
			din = $urandom();
		end
	end
	
  
  // Coverage of state transitions
	covergroup cvr_dac1 @(posedge clk);
		
		option.per_instance = 1;
		coverpoint dut.state {
		
			bins out_of_idle = (dut.idle => dut.init); // coming out of idle state bins
		  
			bins init_to_data_gen = (dut.idle => dut.init[*33] => dut.data_gen); // setup to send user data
		  
			bins user_data_send = (dut.data_gen => dut.send[*33] => dut.cont); // sending user data
		  
			bins user_data_cont_to_send = (dut.cont => dut.data_gen); // continue to send user data
		  
			bins stay_in_send_33 = (dut.send[*33]); // stay in send state for 33 clock ticks (32 ticks for data and 1 for acknowledge tick)
		  
			bins stay_in_init_33 = (dut.init[*33]); // stay in init state for 33 clock ticks (32 ticks for dac unique code of 32 bits and 1 for acknowledge tick)
          
			bins back_to_idle =(dut.cont => dut.idle); //start is de-asserted go back to idle state
		}
		
	endgroup
	
	covergroup cvr_dac2 @(posedge clk);
		option.per_instance =1;
		coverpoint mosi{
			bins mosi_low ={0};
			bins mosi_high ={1};
		}
		
		coverpoint cs{
			bins cs_low ={0};
			bins cs_high ={1};
		}
	
	endgroup 
	
	cvr_dac1 ci;
	cvr_dac2 ci2;
	
	initial begin
    	ci = new();
		ci2 = new();
    	$dumpfile("dump.vcd"); 
    	$dumpvars;
    	#2500;
    	$finish();
  end
endmodule

DAC_SPI/result/dump.vcd
$date
Wed Dec 27 01:56:45 2023
$end
$version
Riviera-PRO Version 2022.04.117.8517
$end
$timescale
1 ns
$end

$scope module tb $end
$var reg 1 ! clk $end
$var reg 12 " din [11:0] $end
$var reg 1 # start $end
$var reg 1 $ mosi $end
$var reg 1 % cs $end

$scope module dut $end
$var wire 1 & clk $end
$var wire 12 ' din [11:0] $end
$var wire 1 ( start $end
$var reg 1 ) mosi $end
$var reg 1 * cs $end
$var integer 32 + state $end
$var reg 32 , setup [31:0] $end
$var reg 32 - dac_data [31:0] $end
$var integer 32 . count $end
$upscope $end

$upscope $end

$enddefinitions $end
$dumpvars
0!
bx "
0#
x$
x%
0&
bx '
0(
x)
x*
b0 +
b1000000000000000000000000001 ,
b0 -
b0 .
$end
#5
1!
1&
b1101110011 "
b1101110011 '
1*
0)
1%
0$
#10
0!
0&
#15
1!
1&
b110110101011 "
b110110101011 '
#20
1#
0!
0&
1(
#25
1!
1&
b100010101011 "
b100010101011 '
b1 +
#30
0!
0&
#35
1!
1&
b101001000011 "
b101001000011 '
b1 .
0*
0%
#40
0!
0&
#45
1!
1&
b1111100100 "
b1111100100 '
b10 .
#50
0!
0&
#55
1!
1&
b101100001001 "
b101100001001 '
b11 .
#60
0!
0&
#65
1!
1&
b1101001111 "
b1101001111 '
b100 .
#70
0!
0&
#75
1!
1&
b10001001111 "
b10001001111 '
b101 .
1)
1$
#80
0!
0&
#85
1!
1&
b100001010100 "
b100001010100 '
b110 .
0)
0$
#90
0!
0&
#95
1!
1&
b1 "
b1 '
b111 .
#100
0!
0&
#105
1!
1&
b110101010 "
b110101010 '
b1000 .
#110
0!
0&
#115
1!
1&
b1001100 "
b1001100 '
b1001 .
#120
0!
0&
#125
1!
1&
b11011 "
b11011 '
b1010 .
#130
0!
0&
#135
1!
1&
b1000111001 "
b1000111001 '
b1011 .
#140
0!
0&
#145
1!
1&
b10010010101 "
b10010010101 '
b1100 .
#150
0!
0&
#155
1!
1&
b110111001111 "
b110111001111 '
b1101 .
#160
0!
0&
#165
1!
1&
b101001111011 "
b101001111011 '
b1110 .
#170
0!
0&
#175
1!
1&
b1101101 "
b1101101 '
b1111 .
#180
0!
0&
#185
1!
1&
b111101001110 "
b111101001110 '
b10000 .
#190
0!
0&
#195
1!
1&
b111101111001 "
b111101111001 '
b10001 .
#200
0!
0&
#205
1!
1&
b100101000 "
b100101000 '
b10010 .
#210
0!
0&
#215
1!
1&
b10010100011 "
b10010100011 '
b10011 .
#220
0!
0&
#225
1!
1&
b111110011111 "
b111110011111 '
b10100 .
#230
0!
0&
#235
1!
1&
b101001000100 "
b101001000100 '
b10101 .
#240
0!
0&
#245
1!
1&
b11100001010 "
b11100001010 '
b10110 .
#250
0!
0&
#255
1!
1&
b10110100010 "
b10110100010 '
b10111 .
#260
0!
0&
#265
1!
1&
b10000111111 "
b10000111111 '
b11000 .
#270
0!
0&
#275
1!
1&
b11000100000 "
b11000100000 '
b11001 .
#280
0!
0&
#285
1!
1&
b111101000000 "
b111101000000 '
b11010 .
#290
0!
0&
#295
1!
1&
b101110100100 "
b101110100100 '
b11011 .
#300
0!
0&
#305
1!
1&
b10101110111 "
b10101110111 '
b11100 .
#310
0!
0&
#315
1!
1&
b1110111110 "
b1110111110 '
b11101 .
#320
0!
0&
#325
1!
1&
b1101000 "
b1101000 '
b11110 .
#330
0!
0&
#335
1!
1&
b110001001010 "
b110001001010 '
b11111 .
#340
0!
0&
#345
1!
1&
b10000001000 "
b10000001000 '
b100000 .
1)
1$
#350
0!
0&
#355
1!
1&
b101110101010 "
b101110101010 '
1*
b0 .
b10 +
1%
#360
0!
0&
#365
1!
1&
b100000011101 "
b100000011101 '
b11000010111010101000000000 -
b11 +
#370
0!
0&
#375
1!
1&
b111001111 "
b111001111 '
b1 .
0)
0*
0$
0%
#380
0!
0&
#385
1!
1&
b1001001011 "
b1001001011 '
b10 .
#390
0!
0&
#395
1!
1&
b101010011111 "
b101010011111 '
b11 .
#400
0!
0&
#405
1!
1&
b1011000000 "
b1011000000 '
b100 .
#410
0!
0&
#415
1!
1&
b110000000 "
b110000000 '
b101 .
#420
0!
0&
#425
1!
1&
b101110011010 "
b101110011010 '
b110 .
#430
0!
0&
#435
1!
1&
b111100010110 "
b111100010110 '
b111 .
1)
1$
#440
0!
0&
#445
1!
1&
b101101111011 "
b101101111011 '
b1000 .
#450
0!
0&
#455
1!
1&
b10101101011 "
b10101101011 '
b1001 .
0)
0$
#460
0!
0&
#465
1!
1&
b110111101110 "
b110111101110 '
b1010 .
#470
0!
0&
#475
1!
1&
b110000011111 "
b110000011111 '
b1011 .
#480
0!
0&
#485
1!
1&
b100010000011 "
b100010000011 '
b1100 .
#490
0!
0&
#495
1!
1&
b110101010110 "
b110101010110 '
b1101 .
1)
1$
#500
0!
0&
#505
1!
1&
b100111001001 "
b100111001001 '
b1110 .
0)
0$
#510
0!
0&
#515
1!
1&
b10101110100 "
b10101110100 '
b1111 .
1)
1$
#520
0!
0&
#525
1!
1&
b11110011100 "
b11110011100 '
b10000 .
#530
0!
0&
#535
1!
1&
b101011110011 "
b101011110011 '
b10001 .
#540
0!
0&
#545
1!
1&
b110001010110 "
b110001010110 '
b10010 .
0)
0$
#550
0!
0&
#555
1!
1&
b100011001011 "
b100011001011 '
b10011 .
1)
1$
#560
0!
0&
#565
1!
1&
b111011100010 "
b111011100010 '
b10100 .
0)
0$
#570
0!
0&
#575
1!
1&
b110101010000 "
b110101010000 '
b10101 .
1)
1$
#580
0!
0&
#585
1!
1&
b11111001110 "
b11111001110 '
b10110 .
0)
0$
#590
0!
0&
#595
1!
1&
b100001101100 "
b100001101100 '
b10111 .
1)
1$
#600
0!
0&
#605
1!
1&
b10111000101 "
b10111000101 '
b11000 .
0)
0$
#610
0!
0&
#615
1!
1&
b111110010100 "
b111110010100 '
b11001 .
#620
0!
0&
#625
1!
1&
b111000011100 "
b111000011100 '
b11010 .
#630
0!
0&
#635
1!
1&
b101100000010 "
b101100000010 '
b11011 .
#640
0!
0&
#645
1!
1&
b101001010100 "
b101001010100 '
b11100 .
#650
0!
0&
#655
1!
1&
b111011101000 "
b111011101000 '
b11101 .
#660
0!
0&
#665
1!
1&
b111000011 "
b111000011 '
b11110 .
#670
0!
0&
#675
1!
1&
b10010110101 "
b10010110101 '
b11111 .
#680
0!
0&
#685
1!
1&
b11010111111 "
b11010111111 '
b100000 .
#690
0!
0&
#695
1!
1&
b101110110010 "
b101110110010 '
1*
b0 .
b100 +
1%
#700
0!
0&
#705
1!
1&
b11111111 "
b11111111 '
b10 +
#710
0!
0&
#715
1!
1&
b110101110111 "
b110101110111 '
b11000000001111111100000000 -
b11 +
#720
0!
0&
#725
1!
1&
b101100010110 "
b101100010110 '
b1 .
0*
0%
#730
0!
0&
#735
1!
1&
b101000001000 "
b101000001000 '
b10 .
#740
0!
0&
#745
1!
1&
b111100101010 "
b111100101010 '
b11 .
#750
0!
0&
#755
1!
1&
b100010011101 "
b100010011101 '
b100 .
#760
0!
0&
#765
1!
1&
b111101010111 "
b111101010111 '
b101 .
#770
0!
0&
#775
1!
1&
b10101100011 "
b10101100011 '
b110 .
#780
0!
0&
#785
1!
1&
b1100001 "
b1100001 '
b111 .
1)
1$
#790
0!
0&
#795
1!
1&
b110110010 "
b110110010 '
b1000 .
#800
0!
0&
#805
1!
1&
b110100110 "
b110100110 '
b1001 .
0)
0$
#810
0!
0&
#815
1!
1&
b101110010010 "
b101110010010 '
b1010 .
#820
0!
0&
#825
1!
1&
b101101100111 "
b101101100111 '
b1011 .
#830
0!
0&
#835
1!
1&
b1010001000 "
b1010001000 '
b1100 .
#840
0!
0&
#845
1!
1&
b10011011110 "
b10011011110 '
b1101 .
#850
0!
0&
#855
1!
1&
b1011110010 "
b1011110010 '
b1110 .
#860
0!
0&
#865
1!
1&
b10111001000 "
b10111001000 '
b1111 .
#870
0!
0&
#875
1!
1&
b11010001111 "
b11010001111 '
b10000 .
#880
0!
0&
#885
1!
1&
b1101001000 "
b1101001000 '
b10001 .
1)
1$
#890
0!
0&
#895
1!
1&
b111111011100 "
b111111011100 '
b10010 .
#900
0!
0&
#905
1!
1&
b111001000001 "
b111001000001 '
b10011 .
#910
0!
0&
#915
1!
1&
b111101101001 "
b111101101001 '
b10100 .
#920
0!
0&
#925
1!
1&
b100110101001 "
b100110101001 '
b10101 .
#930
0!
0&
#935
1!
1&
b110101011101 "
b110101011101 '
b10110 .
#940
0!
0&
#945
1!
1&
b100101011111 "
b100101011111 '
b10111 .
#950
0!
0&
#955
1!
1&
b111010111101 "
b111010111101 '
b11000 .
#960
0!
0&
#965
1!
1&
b111010000001 "
b111010000001 '
b11001 .
0)
0$
#970
0!
0&
#975
1!
1&
b110100101100 "
b110100101100 '
b11010 .
#980
0!
0&
#985
1!
1&
b10001100101 "
b10001100101 '
b11011 .
#990
0!
0&
#995
1!
1&
b100101001010 "
b100101001010 '
b11100 .
#1000
0!
0&
#1005
1!
1&
b100110010010 "
b100110010010 '
b11101 .
#1010
0!
0&
#1015
1!
1&
b1011011000 "
b1011011000 '
b11110 .
#1020
0!
0&
#1025
1!
1&
b1001110010 "
b1001110010 '
b11111 .
#1030
0!
0&
#1035
1!
1&
b11100111111 "
b11100111111 '
b100000 .
#1040
0!
0&
#1045
1!
1&
b111110011110 "
b111110011110 '
1*
b0 .
b100 +
1%
#1050
0!
0&
#1055
1!
1&
b111001000001 "
b111001000001 '
b10 +
#1060
0!
0&
#1065
1!
1&
b11111100011 "
b11111100011 '
b11000011100100000100000000 -
b11 +
#1070
0!
0&
#1075
1!
1&
b10111001010 "
b10111001010 '
b1 .
0*
0%
#1080
0!
0&
#1085
1!
1&
b11001110101 "
b11001110101 '
b10 .
#1090
0!
0&
#1095
1!
1&
b100101001000 "
b100101001000 '
b11 .
#1100
0!
0&
#1105
1!
1&
b11111110101 "
b11111110101 '
b100 .
#1110
0!
0&
#1115
1!
1&
b110111101111 "
b110111101111 '
b101 .
#1120
0!
0&
#1125
1!
1&
b10100101110 "
b10100101110 '
b110 .
#1130
0!
0&
#1135
1!
1&
b110011001010 "
b110011001010 '
b111 .
1)
1$
#1140
0!
0&
#1145
1!
1&
b100010101111 "
b100010101111 '
b1000 .
#1150
0!
0&
#1155
1!
1&
b10010011010 "
b10010011010 '
b1001 .
0)
0$
#1160
0!
0&
#1165
1!
1&
b10010110100 "
b10010110100 '
b1010 .
#1170
0!
0&
#1175
1!
1&
b11001001 "
b11001001 '
b1011 .
#1180
0!
0&
#1185
1!
1&
b11111110 "
b11111110 '
b1100 .
#1190
0!
0&
#1195
1!
1&
b11111110110 "
b11111110110 '
b1101 .
1)
1$
#1200
0!
0&
#1205
1!
1&
b10010000100 "
b10010000100 '
b1110 .
#1210
0!
0&
#1215
1!
1&
b101111101100 "
b101111101100 '
b1111 .
#1220
0!
0&
#1225
1!
1&
b10100100001 "
b10100100001 '
b10000 .
0)
0$
#1230
0!
0&
#1235
1!
1&
b110111111111 "
b110111111111 '
b10001 .
#1240
0!
0&
#1245
1!
1&
b11110110100 "
b11110110100 '
b10010 .
1)
1$
#1250
0!
0&
#1255
1!
1&
b11000101001 "
b11000101001 '
b10011 .
0)
0$
#1260
0!
0&
#1265
1!
1&
b10101000111 "
b10101000111 '
b10100 .
#1270
0!
0&
#1275
1!
1&
b100001010110 "
b100001010110 '
b10101 .
#1280
0!
0&
#1285
1!
1&
b111000110110 "
b111000110110 '
b10110 .
#1290
0!
0&
#1295
1!
1&
b1011000000 "
b1011000000 '
b10111 .
#1300
0!
0&
#1305
1!
1&
b1001110101 "
b1001110101 '
b11000 .
1)
1$
#1310
0!
0&
#1315
1!
1&
b101010011 "
b101010011 '
b11001 .
0)
0$
#1320
0!
0&
#1325
1!
1&
b111001011110 "
b111001011110 '
b11010 .
#1330
0!
0&
#1335
1!
1&
b10101101010 "
b10101101010 '
b11011 .
#1340
0!
0&
#1345
1!
1&
b110110101101 "
b110110101101 '
b11100 .
#1350
0!
0&
#1355
1!
1&
b11001100000 "
b11001100000 '
b11101 .
#1360
0!
0&
#1365
1!
1&
b1010100001 "
b1010100001 '
b11110 .
#1370
0!
0&
#1375
1!
1&
b11011010010 "
b11011010010 '
b11111 .
#1380
0!
0&
#1385
1!
1&
b10101001100 "
b10101001100 '
b100000 .
#1390
0!
0&
#1395
1!
1&
b1110000100 "
b1110000100 '
1*
b0 .
b100 +
1%
#1400
0!
0&
#1405
1!
1&
b111110011110 "
b111110011110 '
b10 +
#1410
0!
0&
#1415
1!
1&
b110001000100 "
b110001000100 '
b11000011111001111000000000 -
b11 +
#1420
0!
0&
#1425
1!
1&
b10010110011 "
b10010110011 '
b1 .
0*
0%
#1430
0!
0&
#1435
1!
1&
b10000111110 "
b10000111110 '
b10 .
#1440
0!
0&
#1445
1!
1&
b11001100010 "
b11001100010 '
b11 .
#1450
0!
0&
#1455
1!
1&
b11010100011 "
b11010100011 '
b100 .
#1460
0!
0&
#1465
1!
1&
b101000101010 "
b101000101010 '
b101 .
#1470
0!
0&
#1475
1!
1&
b110110010100 "
b110110010100 '
b110 .
#1480
0!
0&
#1485
1!
1&
b11011100111 "
b11011100111 '
b111 .
1)
1$
#1490
0!
0&
#1495
1!
1&
b110010100000 "
b110010100000 '
b1000 .
#1500
0!
0&
#1505
1!
1&
b11100000000 "
b11100000000 '
b1001 .
0)
0$
#1510
0!
0&
#1515
1!
1&
b10101101010 "
b10101101010 '
b1010 .
#1520
0!
0&
#1525
1!
1&
b11011011110 "
b11011011110 '
b1011 .
#1530
0!
0&
#1535
1!
1&
b10000101000 "
b10000101000 '
b1100 .
#1540
0!
0&
#1545
1!
1&
b110111110110 "
b110111110110 '
b1101 .
1)
1$
#1550
0!
0&
#1555
1!
1&
b101100010111 "
b101100010111 '
b1110 .
#1560
0!
0&
#1565
1!
1&
b10101110 "
b10101110 '
b1111 .
#1570
0!
0&
#1575
1!
1&
b111100011110 "
b111100011110 '
b10000 .
#1580
0!
0&
#1585
1!
1&
b1111011100 "
b1111011100 '
b10001 .
#1590
0!
0&
#1595
1!
1&
b10100110101 "
b10100110101 '
b10010 .
0)
0$
#1600
0!
0&
#1605
1!
1&
b111010111011 "
b111010111011 '
b10011 .
#1610
0!
0&
#1615
1!
1&
b111101001010 "
b111101001010 '
b10100 .
1)
1$
#1620
0!
0&
#1625
1!
1&
b11001111100 "
b11001111100 '
b10101 .
#1630
0!
0&
#1635
1!
1&
b100010111000 "
b100010111000 '
b10110 .
#1640
0!
0&
#1645
1!
1&
b11011101011 "
b11011101011 '
b10111 .
#1650
0!
0&
#1655
1!
1&
b10110010000 "
b10110010000 '
b11000 .
0)
0$
#1660
0!
0&
#1665
1!
1&
b110110110111 "
b110110110111 '
b11001 .
#1670
0!
0&
#1675
1!
1&
b110101000001 "
b110101000001 '
b11010 .
#1680
0!
0&
#1685
1!
1&
b101001100101 "
b101001100101 '
b11011 .
#1690
0!
0&
#1695
1!
1&
b1100100 "
b1100100 '
b11100 .
#1700
0!
0&
#1705
1!
1&
b101011101110 "
b101011101110 '
b11101 .
#1710
0!
0&
#1715
1!
1&
b1010110100 "
b1010110100 '
b11110 .
#1720
0!
0&
#1725
1!
1&
b110110011011 "
b110110011011 '
b11111 .
#1730
0!
0&
#1735
1!
1&
b110101111101 "
b110101111101 '
b100000 .
#1740
0!
0&
#1745
1!
1&
b101010100011 "
b101010100011 '
1*
b0 .
b100 +
1%
#1750
0!
0&
#1755
1!
1&
b110000000111 "
b110000000111 '
b10 +
#1760
0!
0&
#1765
1!
1&
b110010001010 "
b110010001010 '
b11000011000000011100000000 -
b11 +
#1770
0!
0&
#1775
1!
1&
b1011001000 "
b1011001000 '
b1 .
0*
0%
#1780
0!
0&
#1785
1!
1&
b110001011111 "
b110001011111 '
b10 .
#1790
0!
0&
#1795
1!
1&
b1101011101 "
b1101011101 '
b11 .
#1800
0!
0&
#1805
1!
1&
b111101000000 "
b111101000000 '
b100 .
#1810
0!
0&
#1815
1!
1&
b1010011111 "
b1010011111 '
b101 .
#1820
0!
0&
#1825
1!
1&
b10011010101 "
b10011010101 '
b110 .
#1830
0!
0&
#1835
1!
1&
b101101010011 "
b101101010011 '
b111 .
1)
1$
#1840
0!
0&
#1845
1!
1&
b1010011110 "
b1010011110 '
b1000 .
#1850
0!
0&
#1855
1!
1&
b111100111010 "
b111100111010 '
b1001 .
0)
0$
#1860
0!
0&
#1865
1!
1&
b111001000111 "
b111001000111 '
b1010 .
#1870
0!
0&
#1875
1!
1&
b110011000 "
b110011000 '
b1011 .
#1880
0!
0&
#1885
1!
1&
b100101011111 "
b100101011111 '
b1100 .
#1890
0!
0&
#1895
1!
1&
b101100101 "
b101100101 '
b1101 .
1)
1$
#1900
0!
0&
#1905
1!
1&
b101100101000 "
b101100101000 '
b1110 .
#1910
0!
0&
#1915
1!
1&
b11011000010 "
b11011000010 '
b1111 .
0)
0$
#1920
0!
0&
#1925
1!
1&
b100101011000 "
b100101011000 '
b10000 .
#1930
0!
0&
#1935
1!
1&
b11001110011 "
b11001110011 '
b10001 .
#1940
0!
0&
#1945
1!
1&
b111100000010 "
b111100000010 '
b10010 .
#1950
0!
0&
#1955
1!
1&
b111101100000 "
b111101100000 '
b10011 .
#1960
0!
0&
#1965
1!
1&
b100100000001 "
b100100000001 '
b10100 .
#1970
0!
0&
#1975
1!
1&
b100101110010 "
b100101110010 '
b10101 .
#1980
0!
0&
#1985
1!
1&
b110011001 "
b110011001 '
b10110 .
1)
1$
#1990
0!
0&
#1995
1!
1&
b1001001011 "
b1001001011 '
b10111 .
#2000
0!
0&
#2005
1!
1&
b11000 .
#2010
0!
0&
#2015
1!
1&
b11001 .
0)
0$
#2020
0#
0!
0&
0(
#2025
1!
1&
b11010 .
#2030
0!
0&
#2035
1!
1&
b11011 .
#2040
0!
0&
#2045
1!
1&
b11100 .
#2050
0!
0&
#2055
1!
1&
b11101 .
#2060
0!
0&
#2065
1!
1&
b11110 .
#2070
0!
0&
#2075
1!
1&
b11111 .
#2080
0!
0&
#2085
1!
1&
b100000 .
#2090
0!
0&
#2095
1!
1&
1*
b0 .
b100 +
1%
#2100
0!
0&
#2105
1!
1&
b0 +
