MUX_8x1/result/design.sv
module mux
  (
input a,b,c,d,e,f,g,h,
    input [2:0] sel,
output reg y
  );
 
  
  always@(*)
    begin
      case(sel)
       0: y = a;
       1: y = b;
       2: y = c;
       3: y = d;
       4: y = e;
       5: y = f;
       6: y = g;
       7: y = h;
       default : y = 0;
      endcase
    end
  
  
  
endmodule

MUX_8x1/result/testbench.sv
`timescale 1ns/1ns 

module tb;
	logic a,b,c,d,e,f,g,h;
	logic [2:0] sel;
	logic y;
	
  mux DUT (a,b,c,d,e,f,g,h,sel,y);
	
	covergroup cvr_mux;
		option.per_instance = 1;
		
		coverpoint a {
			bins a_low = {0};
			bins a_high = {1};
		}
		
		coverpoint b {
			bins b_low = {0};
			bins b_high = {1};
		}
		
		coverpoint c {
			bins c_low = {0};
			bins c_high = {1};
		}
		
		coverpoint d {
			bins d_low = {0};
			bins d_high = {1};
		}
		
		coverpoint e {
			bins e_low = {0};
			bins e_high = {1};
		}
		
		coverpoint f {
			bins f_low = {0};
			bins f_high = {1};
		}
		
		coverpoint g {
			bins g_low = {0};
			bins g_high = {1};
		}
		
		coverpoint h {
			bins h_low = {0};
			bins h_high = {1};
		}

		cross sel,a {
			ignore_bins other_bins = binsof (sel) intersect {[1:7]}; // a occurs when sel=0, other values if sel are useless
		}
		
		cross sel,b {
			ignore_bins other_bins = binsof (sel) intersect {0,[2:7]}; // b occurs when sel=1, other values if sel are useless
		}
		
		cross sel,c {
			ignore_bins other_bins = binsof (sel) intersect {[0:1],[3:7]}; // c occurs when sel=2, other values if sel are useless
		}
		
		cross sel,d {
			ignore_bins other_bins = binsof (sel) intersect {[0:2],[4:7]}; // d occurs when sel=3, other values if sel are useless
		}
		
		cross sel,e {
			ignore_bins other_bins = binsof (sel) intersect {[0:3],[5:7]}; // e occurs when sel=4, other values if sel are useless
		}
		
		cross sel,f {
			ignore_bins other_bins = binsof (sel) intersect {[0:4],[6:7]}; // f occurs when sel=5, other values if sel are useless
		}
		
		cross sel,g {
			ignore_bins other_bins = binsof (sel) intersect {[0:5],7}; // g occurs when sel=6, other values if sel are useless
		}
		
		cross sel,h {
			ignore_bins other_bins = binsof (sel) intersect {[0:6]}; // h occurs when sel=7, other values if sel are useless
		}
		
		coverpoint sel;
		coverpoint y;
		
	endgroup
	
	
	cvr_mux c1;
	
	initial begin
		c1 = new();
		for (int i=0; i<100 ;i++) begin
		sel = $urandom();
		{a,b,c,d,e,f,g,h} = $urandom();
		c1.sample();
		#10;
		end
	end
	
	initial begin
		$dumpfile("dump.vcd");
		$dumpvars;
		#1500;
		$finish();
	
	end
endmodule

MUX_8x1/result/dump.vcd
$date
Tue Dec 26 05:22:58 2023
$end
$version
Riviera-PRO Version 2022.04.117.8517
$end
$timescale
1 ns
$end

$scope module tb $end
$var reg 1 ! a $end
$var reg 1 " b $end
$var reg 1 # c $end
$var reg 1 $ d $end
$var reg 1 % e $end
$var reg 1 & f $end
$var reg 1 ' g $end
$var reg 1 ( h $end
$var reg 3 ) sel [2:0] $end
$var reg 1 * y $end

$scope module DUT $end
$var wire 1 + a $end
$var wire 1 , b $end
$var wire 1 - c $end
$var wire 1 . d $end
$var wire 1 / e $end
$var wire 1 0 f $end
$var wire 1 1 g $end
$var wire 1 2 h $end
$var wire 3 3 sel [2:0] $end
$var reg 1 4 y $end
$upscope $end

$upscope $end

$enddefinitions $end
$dumpvars
1!
0"
0#
0$
0%
0&
1'
0(
b101 )
0*
1+
0,
0-
0.
0/
00
11
02
b101 3
04
$end
#10
1$
1#
1"
0!
0+
1,
1-
1.
#20
1(
0'
0#
0-
01
12
#30
b100 )
0(
1%
0$
0"
1!
1+
0,
0.
1/
02
b100 3
14
1*
#40
b0 )
1'
1#
1"
1,
1-
11
b0 3
#50
b10 )
0#
0-
b10 3
04
0*
#60
b110 )
1$
1#
0!
0+
1-
1.
b110 3
14
1*
#70
b11 )
1(
0%
0$
0#
0"
1!
1+
0,
0-
0.
0/
12
b11 3
04
0*
#80
b100 )
1&
1$
0!
0+
1.
10
b100 3
#90
b101 )
0$
1!
1+
0.
b101 3
14
1*
#100
b10 )
0(
1%
1"
1,
1/
02
b10 3
04
0*
#110
b110 )
1(
0'
0%
1#
0!
0+
1-
0/
01
12
b110 3
#120
0(
1%
1$
1!
1+
1.
1/
02
#130
b1 )
1(
0&
0#
0-
00
12
b1 3
14
1*
#140
b10 )
0(
1&
10
02
b10 3
04
0*
#150
b1 )
0%
0$
0"
0,
0.
0/
b1 3
#160
b10 )
1(
0&
1#
1"
0!
0+
1,
1-
00
12
b10 3
14
1*
#170
b101 )
0(
1'
1&
1%
1$
0#
1!
1+
0-
1.
1/
10
11
02
b101 3
#180
b1 )
0%
0$
0!
0+
0.
0/
b1 3
#190
b101 )
1(
0&
1%
1#
1-
1/
00
12
b101 3
04
0*
#200
b100 )
0(
0%
0/
02
b100 3
#210
b101 )
0'
1&
1%
0"
0,
1/
10
01
b101 3
14
1*
#220
b0 )
0&
0%
0#
1"
1,
0-
0/
00
b0 3
04
0*
#230
b111 )
1%
1$
1.
1/
b111 3
#240
b0 )
1(
1'
1&
0$
1#
1!
1+
1-
0.
10
11
12
b0 3
14
1*
#250
b110 )
0&
0#
0!
0+
0-
00
b110 3
#260
b10 )
0'
1&
0%
1$
0"
0,
1.
0/
10
01
b10 3
04
0*
#270
b1 )
0(
1'
1%
1#
1!
1+
1-
1/
11
02
b1 3
#280
b100 )
0&
0$
0#
1"
0!
0+
1,
0-
0.
00
b100 3
14
1*
#290
b101 )
0'
1$
1#
0"
0,
1-
1.
01
b101 3
04
0*
#300
b1 )
1'
0%
0$
1!
1+
0.
0/
11
b1 3
#310
b0 )
0'
1&
0#
1"
1,
0-
10
01
b0 3
14
1*
#320
1(
1'
0&
1%
0"
0,
1/
00
11
12
#330
b1 )
0(
0'
1&
0%
1#
1"
1,
1-
0/
10
01
02
b1 3
#340
b111 )
1'
0&
1%
1$
0#
0-
1.
1/
00
11
b111 3
04
0*
#350
b100 )
1(
0'
1&
0%
0$
0.
0/
10
01
12
b100 3
#360
b101 )
1'
1%
1$
0"
0!
0+
0,
1.
1/
11
b101 3
14
1*
#370
0&
0%
1#
1!
1+
1-
0/
00
04
0*
#380
b110 )
0(
0'
0$
0#
1"
0!
0+
1,
0-
0.
01
02
b110 3
#390
b11 )
1(
1'
1&
1%
1!
1+
1/
10
11
12
b11 3
#400
0'
0%
0!
0+
0/
01
#410
b111 )
0(
1'
1%
1$
1#
1!
1+
1-
1.
1/
11
02
b111 3
#420
b1 )
0'
0&
0%
0!
0+
0/
00
01
b1 3
14
1*
#430
b110 )
1&
0$
0"
0,
0.
10
b110 3
04
0*
#440
b1 )
0&
1$
0#
1!
1+
0-
1.
00
b1 3
#450
b100 )
1(
12
b100 3
#460
b0 )
0(
1'
1&
10
11
02
b0 3
14
1*
#470
b1 )
1(
0&
1%
1#
1-
1/
00
12
b1 3
04
0*
#480
0(
0'
0$
1"
0!
0+
1,
0.
01
02
14
1*
#490
1(
1&
0"
0,
10
12
04
0*
#500
b0 )
0%
1$
1"
1!
1+
1,
1.
0/
b0 3
14
1*
#510
1'
1%
0"
0,
1/
11
#520
b1 )
0(
0'
0&
0$
0#
0-
0.
00
01
02
b1 3
04
0*
#530
b11 )
1(
1'
1&
0%
0!
0+
0/
10
11
12
b11 3
#540
b1 )
0'
0&
1#
1"
1,
1-
00
01
b1 3
14
1*
#550
b101 )
1'
1&
1%
0#
0"
0,
0-
1/
10
11
b101 3
#560
b11 )
0'
0&
0%
1!
1+
0/
00
01
b11 3
04
0*
#570
b1 )
1'
1&
1"
0!
0+
1,
10
11
b1 3
14
1*
#580
b110 )
0'
1!
1+
01
b110 3
04
0*
#590
b11 )
1%
1$
1#
0"
0,
1-
1.
1/
b11 3
14
1*
#600
b101 )
0(
1'
0%
0!
0+
0/
11
02
b101 3
#610
b100 )
1(
0&
1%
0$
0#
1!
1+
0-
0.
1/
00
12
b100 3
#620
b0 )
1&
1$
1.
10
b0 3
#630
b110 )
0$
0.
b110 3
#640
b10 )
0(
1$
1"
0!
0+
1,
1.
02
b10 3
04
0*
#650
b110 )
1(
0'
0&
0%
0$
1#
1-
0.
0/
00
01
12
b110 3
#660
b100 )
1'
1&
1%
1$
1.
1/
10
11
b100 3
14
1*
#670
b0 )
0'
0&
0%
0$
0#
0"
1!
1+
0,
0-
0.
0/
00
01
b0 3
#680
0(
1'
1&
0!
0+
10
11
02
04
0*
#690
0'
0&
1$
1"
1!
1+
1,
1.
00
01
14
1*
#700
1(
1'
1%
0$
0"
0,
0.
1/
11
12
#710
b110 )
0'
0%
1"
0!
0+
1,
0/
01
b110 3
04
0*
#720
b0 )
0(
1&
1%
0"
0,
1/
10
02
b0 3
#730
b10 )
0&
0%
1$
1"
1!
1+
1,
1.
0/
00
b10 3
#740
1'
1&
1%
1#
1-
1/
10
11
14
1*
#750
b1 )
0&
0%
0"
0,
0/
00
b1 3
04
0*
#760
1(
0'
1&
0$
0.
10
01
12
#770
b111 )
1%
0#
1"
1,
0-
1/
b111 3
14
1*
#780
b1 )
0%
1#
0"
0,
1-
0/
b1 3
04
0*
#790
b110 )
0(
1'
0&
1%
1"
0!
0+
1,
1/
00
11
02
b110 3
14
1*
#800
0'
1$
0#
1!
1+
0-
1.
01
04
0*
#810
0$
1#
0"
0!
0+
0,
1-
0.
#820
b10 )
0%
1"
1,
0/
b10 3
14
1*
#830
b110 )
1(
1'
1$
0"
0,
1.
11
12
b110 3
#840
b11 )
0(
0'
0$
0#
0-
0.
01
02
b11 3
04
0*
#850
b10 )
1'
1&
1$
1#
1!
1+
1-
1.
10
11
b10 3
14
1*
#860
b100 )
1(
0$
0.
12
b100 3
04
0*
#870
b111 )
0'
1%
0#
0-
1/
01
b111 3
14
1*
#880
b11 )
1"
0!
0+
1,
b11 3
04
0*
#890
1'
1$
1#
0"
0,
1-
1.
11
14
1*
#900
b100 )
0(
0&
0%
0$
0#
0-
0.
0/
00
02
b100 3
04
0*
#910
b1 )
1(
1%
1#
1-
1/
12
b1 3
#920
b101 )
0(
0'
1&
0%
0#
1"
1,
0-
0/
10
01
02
b101 3
14
1*
#930
b11 )
0&
0"
0,
00
b11 3
04
0*
#940
b10 )
1$
1!
1+
1.
b10 3
#950
b1 )
1'
1#
1"
0!
0+
1,
1-
11
b1 3
14
1*
#960
b10 )
1(
1%
0"
0,
1/
12
b10 3
#970
0(
0$
0.
02
#980
1(
0'
0%
0#
1!
1+
0-
0/
01
12
04
0*
#990
b1 )
1&
1%
1$
1#
1"
1,
1-
1.
1/
10
b1 3
14
1*
