Periority_encoder/result/design.sv
module penc(
  input [7:0]y,
  output reg [2:0] a
);
  
  always@(y)
  begin
    casez(y)
 
  8'b00000001:a = 3'b000;
  8'b0000001?:a = 3'b001;
  8'b000001??:a = 3'b010;
  8'b00001???:a = 3'b011;
  8'b0001????:a = 3'b100;
  8'b001?????:a = 3'b101;
  8'b01??????:a = 3'b110;
  8'b1???????:a = 3'b111;
 
  default:a = 3'bzzz;
  endcase
 end
  
endmodule

Periority_encoder/result/testbench.sv
module tb;
	logic [7:0] y;
	logic [2:0] a;
	
	
	penc DUT (y,a);
	
	covergroup cvr_penc;
		option.per_instance = 1;
		
		coverpoint y{
					 bins zero  ={8'b0000_0001};
			wildcard bins one   ={8'b0000_001?};
			wildcard bins two   ={8'b0000_01??};
			wildcard bins three ={8'b0000_1???};
			wildcard bins four  ={8'b0001_????};
			wildcard bins five  ={8'b001?_????};
			wildcard bins six   ={8'b01??_????};
			wildcard bins seven ={8'b1???_????};		
		}
		
		coverpoint a;
	endgroup
	
	cvr_penc c1;
	
	initial begin
		c1 = new();
      for (int i=0; i<300 ; i++)begin
			y=$urandom();
			c1.sample();
			#10;
		end
	end
	
	initial begin
		$dumpfile("dump.vcd");
		$dumpvars;
		#3000;
		$finish;
	end
endmodule

Periority_encoder/result/dump.vcd
$date
Tue Dec 26 11:02:27 2023
$end
$version
Riviera-PRO Version 2022.04.117.8517
$end
$timescale
1 ns
$end

$scope module tb $end
$var reg 8 ! y [7:0] $end
$var reg 3 " a [2:0] $end

$scope module DUT $end
$var wire 8 # y [7:0] $end
$var reg 3 $ a [2:0] $end
$upscope $end

$upscope $end

$enddefinitions $end
$dumpvars
b11001101 !
b111 "
b11001101 #
b111 $
$end
#10
b10000010 !
b10000010 #
#20
b1111101 !
b1111101 #
b110 $
b110 "
#30
b1110010 !
b1110010 #
#40
b1011101 !
b1011101 #
#50
b1010001 !
b1010001 #
#60
b1011100 !
b1011100 #
#70
b10001000 !
b10001000 #
b111 $
b111 "
#80
b1110000 !
b1110000 #
b110 $
b110 "
#90
b11101010 !
b11101010 #
b111 $
b111 "
#110
b11001010 !
b11001010 #
#120
b11000110 !
b11000110 #
#130
b1111010 !
b1111010 #
b110 $
b110 "
#140
b1100011 !
b1100011 #
#150
b10000011 !
b10000011 #
b111 $
b111 "
#160
b1010100 !
b1010100 #
b110 $
b110 "
#170
b10111 !
b10111 #
b100 $
b100 "
#180
b11101 !
b11101 #
#190
b10000111 !
b10000111 #
b111 $
b111 "
#200
b100010 !
b100010 #
b101 $
b101 "
#210
b11001110 !
b11001110 #
b111 $
b111 "
#220
b1110 !
b1110 #
b11 $
b11 "
#230
b1100101 !
b1100101 #
b110 $
b110 "
#240
b1110110 !
b1110110 #
#250
b11111100 !
b11111100 #
b111 $
b111 "
#260
b10010001 !
b10010001 #
#270
b11011001 !
b11011001 #
#280
b110010 !
b110010 #
b101 $
b101 "
#290
b11011100 !
b11011100 #
b111 $
b111 "
#300
b1101001 !
b1101001 #
b110 $
b110 "
#310
b10000100 !
b10000100 #
b111 $
b111 "
#320
b1111010 !
b1111010 #
b110 $
b110 "
#330
b1100001 !
b1100001 #
#340
b101 !
b101 #
b10 $
b10 "
#350
b11011110 !
b11011110 #
b111 $
b111 "
#360
b10011001 !
b10011001 #
#370
b1000110 !
b1000110 #
b110 $
b110 "
#380
b101 !
b101 #
b10 $
b10 "
#390
b1101011 !
b1101011 #
b110 $
b110 "
#400
b100100 !
b100100 #
b101 $
b101 "
#410
b1100010 !
b1100010 #
b110 $
b110 "
#420
b11111101 !
b11111101 #
b111 $
b111 "
#430
b101100 !
b101100 #
b101 $
b101 "
#440
b1100000 !
b1100000 #
b110 $
b110 "
#450
b1000000 !
b1000000 #
#460
b1110111 !
b1110111 #
#470
b1011000 !
b1011000 #
#480
b11100000 !
b11100000 #
b111 $
b111 "
#490
b11101111 !
b11101111 #
#500
b111110 !
b111110 #
b101 $
b101 "
#510
b1001011 !
b1001011 #
b110 $
b110 "
#520
b1110010 !
b1110010 #
#530
b10101 !
b10101 #
b100 $
b100 "
#540
b11011001 !
b11011001 #
b111 $
b111 "
#550
b10111110 !
b10111110 #
#560
b111100 !
b111100 #
b101 $
b101 "
#570
b1001010 !
b1001010 #
b110 $
b110 "
#580
b1010101 !
b1010101 #
#590
b111000 !
b111000 #
b101 $
b101 "
#600
b100001 !
b100001 #
#610
b10100010 !
b10100010 #
b111 $
b111 "
#620
b1001000 !
b1001000 #
b110 $
b110 "
#630
b11000100 !
b11000100 #
b111 $
b111 "
#640
b1101000 !
b1101000 #
b110 $
b110 "
#650
b10001011 !
b10001011 #
b111 $
b111 "
#660
b10001 !
b10001 #
b100 $
b100 "
#670
b11100100 !
b11100100 #
b111 $
b111 "
#680
b10011111 !
b10011111 #
#690
b11011010 !
b11011010 #
#700
b1100100 !
b1100100 #
b110 $
b110 "
#710
b11000101 !
b11000101 #
b111 $
b111 "
#720
b10111101 !
b10111101 #
#730
b11111 !
b11111 #
b100 $
b100 "
#740
b101 !
b101 #
b10 $
b10 "
#750
b10110011 !
b10110011 #
b111 $
b111 "
#760
b10000110 !
b10000110 #
#770
b1000000 !
b1000000 #
b110 $
b110 "
#780
b11010011 !
b11010011 #
b111 $
b111 "
#790
b11001111 !
b11001111 #
#800
b110011 !
b110011 #
b101 $
b101 "
#810
b1000101 !
b1000101 #
b110 $
b110 "
#820
b111 !
b111 #
b10 $
b10 "
#830
b11111110 !
b11111110 #
b111 $
b111 "
#840
b1010001 !
b1010001 #
b110 $
b110 "
#850
b1110000 !
b1110000 #
#860
b10111110 !
b10111110 #
b111 $
b111 "
#870
b100100 !
b100100 #
b101 $
b101 "
#880
b11101001 !
b11101001 #
b111 $
b111 "
#890
b10010000 !
b10010000 #
#900
b10110100 !
b10110100 #
#910
b10010001 !
b10010001 #
#920
b11100000 !
b11100000 #
#930
b10010110 !
b10010110 #
#940
b1010001 !
b1010001 #
b110 $
b110 "
#950
b10111011 !
b10111011 #
b111 $
b111 "
#960
b10100001 !
b10100001 #
#970
b1101000 !
b1101000 #
b110 $
b110 "
#980
b11101001 !
b11101001 #
b111 $
b111 "
#990
b101101 !
b101101 #
b101 $
b101 "
#1000
b11111000 !
b11111000 #
b111 $
b111 "
#1010
b11110101 !
b11110101 #
#1020
b1000000 !
b1000000 #
b110 $
b110 "
#1030
b10111111 !
b10111111 #
b111 $
b111 "
#1040
b1000001 !
b1000001 #
b110 $
b110 "
#1050
b10001000 !
b10001000 #
b111 $
b111 "
#1060
b1001011 !
b1001011 #
b110 $
b110 "
#1070
b111 !
b111 #
b10 $
b10 "
#1080
b11000001 !
b11000001 #
b111 $
b111 "
#1090
b1100001 !
b1100001 #
b110 $
b110 "
#1100
b111101 !
b111101 #
b101 $
b101 "
#1110
b1111 !
b1111 #
b11 $
b11 "
#1120
b1010011 !
b1010011 #
b110 $
b110 "
#1130
b10000001 !
b10000001 #
b111 $
b111 "
#1140
b11000001 !
b11000001 #
#1150
b1000111 !
b1000111 #
b110 $
b110 "
#1160
b1000110 !
b1000110 #
#1170
b11000101 !
b11000101 #
b111 $
b111 "
#1180
b10000011 !
b10000011 #
#1190
b10111101 !
b10111101 #
#1200
b10000101 !
b10000101 #
#1210
b110110 !
b110110 #
b101 $
b101 "
#1220
b11110100 !
b11110100 #
b111 $
b111 "
#1230
b10001011 !
b10001011 #
#1240
b11111000 !
b11111000 #
#1250
b10011111 !
b10011111 #
#1260
b1001110 !
b1001110 #
b110 $
b110 "
#1270
b10001111 !
b10001111 #
b111 $
b111 "
#1280
b101010 !
b101010 #
b101 $
b101 "
#1290
b1011110 !
b1011110 #
b110 $
b110 "
#1300
b11010110 !
b11010110 #
b111 $
b111 "
#1310
b1100001 !
b1100001 #
b110 $
b110 "
#1320
b101100 !
b101100 #
b101 $
b101 "
#1330
b1111111 !
b1111111 #
b110 $
b110 "
#1340
b1100000 !
b1100000 #
#1350
b10000001 !
b10000001 #
b111 $
b111 "
#1360
b10111000 !
b10111000 #
#1370
b110 !
b110 #
b10 $
b10 "
#1380
b11000 !
b11000 #
b100 $
b100 "
#1390
b11010000 !
b11010000 #
b111 $
b111 "
#1400
b10011000 !
b10011000 #
#1410
b10001011 !
b10001011 #
#1420
b1111110 !
b1111110 #
b110 $
b110 "
#1430
b1000001 !
b1000001 #
#1440
b1001000 !
b1001000 #
#1450
b1100 !
b1100 #
b11 $
b11 "
#1460
b10110010 !
b10110010 #
b111 $
b111 "
#1470
b11010000 !
b11010000 #
#1480
b11011010 !
b11011010 #
#1490
b11111110 !
b11111110 #
#1500
b11110001 !
b11110001 #
#1510
b10110010 !
b10110010 #
#1520
b11001 !
b11001 #
b100 $
b100 "
#1530
b10100101 !
b10100101 #
b111 $
b111 "
#1540
b1011111 !
b1011111 #
b110 $
b110 "
#1550
b11001101 !
b11001101 #
b111 $
b111 "
#1560
b11110001 !
b11110001 #
#1570
b10100101 !
b10100101 #
#1580
b110 !
b110 #
b10 $
b10 "
#1590
b1101010 !
b1101010 #
b110 $
b110 "
#1600
b1110 !
b1110 #
b11 $
b11 "
#1610
b11011000 !
b11011000 #
b111 $
b111 "
#1620
b11110 !
b11110 #
b100 $
b100 "
#1630
b101000 !
b101000 #
b101 $
b101 "
#1640
b11000010 !
b11000010 #
b111 $
b111 "
#1650
b1100000 !
b1100000 #
b110 $
b110 "
#1660
b10001110 !
b10001110 #
b111 $
b111 "
#1670
b110011 !
b110011 #
b101 $
b101 "
#1680
b101011 !
b101011 #
#1690
b0 !
b0 #
bz $
bz "
#1700
b10110010 !
b10110010 #
b111 $
b111 "
#1710
b10110110 !
b10110110 #
#1720
b10010100 !
b10010100 #
#1730
b10100111 !
b10100111 #
#1740
b1011111 !
b1011111 #
b110 $
b110 "
#1750
b10001101 !
b10001101 #
b111 $
b111 "
#1760
b11011 !
b11011 #
b100 $
b100 "
#1770
b1001101 !
b1001101 #
b110 $
b110 "
#1780
b100011 !
b100011 #
b101 $
b101 "
#1790
b111111 !
b111111 #
#1800
b10010100 !
b10010100 #
b111 $
b111 "
#1810
b10 !
b10 #
b1 $
b1 "
#1820
b11010001 !
b11010001 #
b111 $
b111 "
#1830
b101011 !
b101011 #
b101 $
b101 "
#1840
b10101101 !
b10101101 #
b111 $
b111 "
#1850
b1000100 !
b1000100 #
b110 $
b110 "
#1860
b111011 !
b111011 #
b101 $
b101 "
#1870
b0 !
b0 #
bz $
bz "
#1880
b1010010 !
b1010010 #
b110 $
b110 "
#1890
b10010000 !
b10010000 #
b111 $
b111 "
#1900
b1000001 !
b1000001 #
b110 $
b110 "
#1910
b1110010 !
b1110010 #
#1920
b1010010 !
b1010010 #
#1930
b111011 !
b111011 #
b101 $
b101 "
#1940
b1010 !
b1010 #
b11 $
b11 "
#1950
b101010 !
b101010 #
b101 $
b101 "
#1960
b1000010 !
b1000010 #
b110 $
b110 "
#1970
b10000001 !
b10000001 #
b111 $
b111 "
#1980
b10010001 !
b10010001 #
#1990
b11111101 !
b11111101 #
#2000
b10100001 !
b10100001 #
#2010
b11011110 !
b11011110 #
#2020
b1100011 !
b1100011 #
b110 $
b110 "
#2030
b1100000 !
b1100000 #
#2040
b111101 !
b111101 #
b101 $
b101 "
#2050
b10011100 !
b10011100 #
b111 $
b111 "
#2060
b10100110 !
b10100110 #
#2070
b11011 !
b11011 #
b100 $
b100 "
#2080
b11010100 !
b11010100 #
b111 $
b111 "
#2090
b10101101 !
b10101101 #
#2100
b1011101 !
b1011101 #
b110 $
b110 "
#2110
b111101 !
b111101 #
b101 $
b101 "
#2120
b11111101 !
b11111101 #
b111 $
b111 "
#2130
b10111010 !
b10111010 #
#2140
b11101001 !
b11101001 #
#2150
b1001111 !
b1001111 #
b110 $
b110 "
#2160
b1001000 !
b1001000 #
#2170
b1111011 !
b1111011 #
#2180
b11010010 !
b11010010 #
b111 $
b111 "
#2190
b11001100 !
b11001100 #
#2200
b10100100 !
b10100100 #
#2210
b1001001 !
b1001001 #
b110 $
b110 "
#2220
b11000111 !
b11000111 #
b111 $
b111 "
#2230
b11001111 !
b11001111 #
#2240
b1 !
b1 #
b0 $
b0 "
#2250
b11110000 !
b11110000 #
b111 $
b111 "
#2260
b11100011 !
b11100011 #
#2270
b1110 !
b1110 #
b11 $
b11 "
#2280
b110110 !
b110110 #
b101 $
b101 "
#2290
b11001010 !
b11001010 #
b111 $
b111 "
#2300
b110001 !
b110001 #
b101 $
b101 "
#2310
b111 !
b111 #
b10 $
b10 "
#2320
b100011 !
b100011 #
b101 $
b101 "
#2330
b1000 !
b1000 #
b11 $
b11 "
#2340
b1110010 !
b1110010 #
b110 $
b110 "
#2350
b1111000 !
b1111000 #
#2360
b11010 !
b11010 #
b100 $
b100 "
#2370
b1010010 !
b1010010 #
b110 $
b110 "
#2380
b11101 !
b11101 #
b100 $
b100 "
#2390
b10011 !
b10011 #
#2400
b1111010 !
b1111010 #
b110 $
b110 "
#2410
b10010011 !
b10010011 #
b111 $
b111 "
#2420
b10100110 !
b10100110 #
#2430
b1110010 !
b1110010 #
b110 $
b110 "
#2440
b10011101 !
b10011101 #
b111 $
b111 "
#2450
b1101 !
b1101 #
b11 $
b11 "
#2460
b11 !
b11 #
b1 $
b1 "
#2470
b1001000 !
b1001000 #
b110 $
b110 "
#2480
b11110011 !
b11110011 #
b111 $
b111 "
#2490
b10110011 !
b10110011 #
#2500
b1101011 !
b1101011 #
b110 $
b110 "
#2510
b11011001 !
b11011001 #
b111 $
b111 "
#2520
b1101110 !
b1101110 #
b110 $
b110 "
#2530
b10110111 !
b10110111 #
b111 $
b111 "
#2540
b1100000 !
b1100000 #
b110 $
b110 "
#2550
b10101011 !
b10101011 #
b111 $
b111 "
#2560
b100001 !
b100001 #
b101 $
b101 "
#2570
b1100000 !
b1100000 #
b110 $
b110 "
#2580
b11101111 !
b11101111 #
b111 $
b111 "
#2590
b1111101 !
b1111101 #
b110 $
b110 "
#2600
b100011 !
b100011 #
b101 $
b101 "
#2610
b100001 !
b100001 #
#2620
b110110 !
b110110 #
#2630
b1111000 !
b1111000 #
b110 $
b110 "
#2640
b10111001 !
b10111001 #
b111 $
b111 "
#2650
b11100111 !
b11100111 #
#2660
b100110 !
b100110 #
b101 $
b101 "
#2670
b10100100 !
b10100100 #
b111 $
b111 "
#2680
b10110011 !
b10110011 #
#2690
b10110010 !
b10110010 #
#2700
b10001010 !
b10001010 #
#2710
b10011101 !
b10011101 #
#2720
b10110 !
b10110 #
b100 $
b100 "
#2730
b1100111 !
b1100111 #
b110 $
b110 "
#2740
b1001000 !
b1001000 #
#2750
b10000101 !
b10000101 #
b111 $
b111 "
#2760
b11111011 !
b11111011 #
#2770
b11100011 !
b11100011 #
#2780
b11100101 !
b11100101 #
#2790
b111100 !
b111100 #
b101 $
b101 "
#2800
b10110110 !
b10110110 #
b111 $
b111 "
#2810
b1010011 !
b1010011 #
b110 $
b110 "
#2820
b1001110 !
b1001110 #
#2830
b11001110 !
b11001110 #
b111 $
b111 "
#2840
b111001 !
b111001 #
b101 $
b101 "
#2850
b11000010 !
b11000010 #
b111 $
b111 "
#2860
b11010100 !
b11010100 #
#2870
b101101 !
b101101 #
b101 $
b101 "
#2880
b10111010 !
b10111010 #
b111 $
b111 "
#2890
b11110011 !
b11110011 #
#2900
b1111000 !
b1111000 #
b110 $
b110 "
#2910
b11111 !
b11111 #
b100 $
b100 "
#2920
b10010100 !
b10010100 #
b111 $
b111 "
#2930
b1110000 !
b1110000 #
b110 $
b110 "
#2940
b1101000 !
b1101000 #
#2950
b1111001 !
b1111001 #
#2960
b1101010 !
b1101010 #
#2970
b11100010 !
b11100010 #
b111 $
b111 "
#2980
b11001001 !
b11001001 #
#2990
b10001101 !
b10001101 #
